fastapi_serviceutils-2.1.0.dist-info/dependency_links.txt
fastapi_serviceutils-2.1.0.dist-info/entry_points.txt
fastapi_serviceutils-2.1.0.dist-info/METADATA
fastapi_serviceutils-2.1.0.dist-info/top_level.txt
fastapi_serviceutils-2.1.0.dist-info/WHEEL
fastapi_serviceutils/__init__.py
fastapi_serviceutils/app/logger.py
fastapi_serviceutils/app/service_config.py
fastapi_serviceutils/app/__init__.py
fastapi_serviceutils/app/middlewares/__init__.py
fastapi_serviceutils/app/handlers/__init__.py
fastapi_serviceutils/app/endpoints/__init__.py
fastapi_serviceutils/app/endpoints/default/models.py
fastapi_serviceutils/app/endpoints/default/alive.py
fastapi_serviceutils/app/endpoints/default/config.py
fastapi_serviceutils/app/endpoints/default/__init__.py
fastapi_serviceutils/utils/__init__.py
fastapi_serviceutils/utils/tests/__init__.py
fastapi_serviceutils/utils/tests/endpoints.py
fastapi_serviceutils/utils/external_resources/services.py
fastapi_serviceutils/utils/external_resources/dbs.py
fastapi_serviceutils/utils/external_resources/__init__.py
fastapi_serviceutils/utils/docs/apidoc.py
fastapi_serviceutils/utils/docs/__init__.py
fastapi_serviceutils/cli/create_service.py
fastapi_serviceutils/cli/__init__.py
fastapi_serviceutils-2.1.0.dist-info/LICENSE
fastapi_serviceutils-2.1.0.dist-info/RECORD