Metadata-Version: 2.1
Name: fastapi-serviceutils
Version: 2.1.0
Summary: Utils for fastapi based services.
Home-Page: https://fastapi-serviceutils.readthedocs.io/en/latest/
Project-URL: Repository, https://github.com/skallfass/fastapi_serviceutils
Author: Simon Kallfass
Author-email: skallfass@ouroboros.info
License: MIT
Requires-Python: <4,>=3.7
Keywords: python,fastapi,webservice,service-utils
Classifier: Operating System :: Unix
Classifier: License :: OSI Approved :: MIT License
Classifier: Programming Language :: Python :: 3.7
Requires-Dist: autoflake>=1.3; extra == "dev"
Requires-Dist: cookiecutter>=1.6
Requires-Dist: coverage-badge>=1; extra == "dev"
Requires-Dist: databases[postgresql]>=0.2
Requires-Dist: fastapi[all]>=0.44
Requires-Dist: flake8>=3.7; extra == "dev"
Requires-Dist: ipython>=7.8; extra == "dev"
Requires-Dist: jedi>=0.14; extra == "dev"
Requires-Dist: loguru>=0.4
Requires-Dist: neovim>=0.3.1; extra == "dev"
Requires-Dist: psycopg2>=2.8
Requires-Dist: pudb>=2019.1; extra == "dev"
Requires-Dist: pygments>=2.4; extra == "dev"
Requires-Dist: pylint>=2.4.3; extra == "dev"
Requires-Dist: pytest>=5; extra == "dev"
Requires-Dist: pytest-asyncio>=0.10; extra == "dev"
Requires-Dist: pytest-cov>=2; extra == "dev"
Requires-Dist: pytest-xdist>=1.30; extra == "dev"
Requires-Dist: requests>=2.22.0
Requires-Dist: sphinx>=2; extra == "dev"
Requires-Dist: sphinx-autodoc-typehints>=1.6; extra == "dev"
Requires-Dist: sphinx-rtd-theme>=0.4.3; extra == "dev"
Requires-Dist: sqlalchemy>=1.3
Requires-Dist: toolz>=0.10
Requires-Dist: yapf>=0.27; extra == "dev"
Provides-Extra: dev
